MANIFEST.in
README.md
setup.cfg
setup.py
nesdict/__init__.py
nesdict/nesdict.py
nesdict.egg-info/PKG-INFO
nesdict.egg-info/SOURCES.txt
nesdict.egg-info/dependency_links.txt
nesdict.egg-info/requires.txt
nesdict.egg-info/top_level.txt
test/test_nesdict.py