Metadata-Version: 1.1
Name: nesdict
Version: 0.1
Summary: Support for xpath-like lookups in nested Python dicts.
Home-page: https://github.com/Kargathia/nesdict
Author: Bob Steers
Author-email: kargathia@hotmail.com
License: UNKNOWN
Download-URL: https://github.com/Kargathia/nesdict/archive/0.1.tar.gz
Keywords: xpath dicts nested lookup
Platform: UNKNOWN
Classifier: Development Status :: 3 - Alpha
Classifier: Intended Audience :: Developers
Classifier: Topic :: Utilities
Classifier: License :: OSI Approved :: MIT License
Classifier: Programming Language :: Python :: 3.4
Classifier: Programming Language :: Python :: 3.5
Classifier: Programming Language :: Python :: 3.6
